[
    {
     "caten": "food",
     "catpe": "خوراک",
     "catid": 10000,
     "pricemin": 1,
     "pricemax": 180,
     "priceavg": 90,
     "icon": "/images/categories/cat_resturant.png",
     "code": "null",
     "parentid": 0,
     "isparent": true
    }
                ,
                    {
                    "caten": "fastfood",
                    "catpe": "فست فود",
                    "catid": 10001,
                    "pricemin": 1,
                    "pricemax": 180,
                    "priceavg": 90,
                    "icon": "/images/categories/cat_resturant.png",
                    "code": "null",
                    "parentid": 10000,
                    "isparent": false
                    }
                ,

    {
    "caten": "clothes",
    "catpe": "لباس",
    "catid": 11000,
    "pricemin": 1,
    "pricemax": 180,
    "priceavg": 90,
    "icon": "/images/categories/cat_shirt.png",
    "code": "null",
    "parentid": 0,
    "isparent": true
    }

                ,
                    {
                        "caten": "tishirt",
                        "catpe": "پیراهن",
                        "catid": 11001,
                        "pricemin": 1,
                        "pricemax": 180,
                        "priceavg": 90,
                        "icon": "/images/categories/cat_shirt.png",
                        "code": "null",
                        "parentid": 11000,
                        "isparent": false
                    }

                ,

    {
    "caten": "home",
    "catpe": "مسکن",
    "catid": 12000,
    "pricemin": 1,
    "pricemax": 180,
    "priceavg": 90,
    "icon": "/images/categories/cat_home.png",
    "code": "null",
    "parentid": 0,
    "isparent": true
    }
            ,
                    {
                    "caten": "home",
                    "catpe": "اجاره منزل",
                    "catid": 12001,
                    "pricemin": 1,
                    "pricemax": 180,
                    "priceavg": 90,
                    "icon": "/images/categories/cat_home.png",
                    "code": "null",
                    "parentid": 12000,
                    "isparent": false
                    }
                    ,
                    {
                    "caten": "home",
                    "catpe": "شارژ ساختمان",
                    "catid": 12002,
                    "pricemin": 1,
                    "pricemax": 180,
                    "priceavg": 90,
                    "icon": "/images/categories/cat_home.png",
                    "code": "null",
                    "parentid": 12000,
                    "isparent": false
                    }
                    ,
                    {
                    "caten": "home",
                    "catpe": "وسایل منزل",
                    "catid": 12003,
                    "pricemin": 1,
                    "pricemax": 180,
                    "priceavg": 90,
                    "icon": "/images/categories/cat_home.png",
                    "code": "null",
                    "parentid": 12000,
                    "isparent": false
                    }
,
    
    {
    "caten": "cigaret",
    "catpe": "سیگار",
    "catid": 13000,
    "pricemin": 1,
    "pricemax": 180,
    "priceavg": 90,
    "icon": "/images/categories/cat_cigret.png",
    "code": "null",
    "parentid": 0,
    "isparent": true
    }
]
   